{"as_of": "2025-10-24T22:08:40+08:00", "source": "Baidu Top Realtime", "items": [{"title": "1. 党的二十届四中全会公报一图速览", "value": "热度 7904725", "url": "https://www.baidu.com/s?wd=%E5%85%9A%E7%9A%84%E4%BA%8C%E5%8D%81%E5%B1%8A%E5%9B%9B%E4%B8%AD%E5%85%A8%E4%BC%9A%E5%85%AC%E6%8A%A5%E4%B8%80%E5%9B%BE%E9%80%9F%E8%A7%88", "extra": {"rank": 1, "raw_score": "7904725", "api_source": "tianapi", "description": "10月20日至23日，中国共产党第二十届中央委员会第四次全体会议在北京举行。党的二十届四中全会公报一图速览，一起来学习。 查看更多&gt;", "translation": "Quick overview of the communiqué from the 20th Central..."}}, {"title": "2. 10月25日设立为台湾光复纪念日", "value": "热度 7808408", "url": "https://www.baidu.com/s?wd=10%E6%9C%8825%E6%97%A5%E8%AE%BE%E7%AB%8B%E4%B8%BA%E5%8F%B0%E6%B9%BE%E5%85%89%E5%A4%8D%E7%BA%AA%E5%BF%B5%E6%97%A5", "extra": {"rank": 2, "raw_score": "7808408", "api_source": "tianapi", "description": "10月24日，十四届全国人大常委会第十八次会议在北京人民大会堂举行第一次全体会议、第二次全体会议。会议表决通过了全国人大常委会关于设立台湾光复纪念日... 查看更多&gt;", "translation": "October 25 designated as Taiwan's Restoration Day..."}}, {"title": "3. “中国天眼”捕获来自星星神秘讯息", "value": "热度 7711839", "url": "https://www.baidu.com/s?wd=%E2%80%9C%E4%B8%AD%E5%9B%BD%E5%A4%A9%E7%9C%BC%E2%80%9D%E6%8D%95%E8%8E%B7%E6%9D%A5%E8%87%AA%E6%98%9F%E6%98%9F%E7%A5%9E%E7%A7%98%E8%AE%AF%E6%81%AF", "extra": {"rank": 3, "raw_score": "7711839", "api_source": "tianapi", "description": "“中国天眼”新发现：北京大学科研团队，首次捕获恒星黑子的磁场射电信号，为研究恒星磁活动对行星宜居性的影响提供重要依据。 查看更多&gt;", "translation": "\"China's Sky Eye\" captures mysterious signals from stars..."}}, {"title": "4. 速览“十四五”中国奔跑姿态", "value": "热度 7617813", "url": "https://www.baidu.com/s?wd=%E9%80%9F%E8%A7%88%E2%80%9C%E5%8D%81%E5%9B%9B%E4%BA%94%E2%80%9D%E4%B8%AD%E5%9B%BD%E5%A5%94%E8%B7%91%E5%A7%BF%E6%80%81", "extra": {"rank": 4, "raw_score": "7617813", "api_source": "tianapi", "description": "经济总量预计约140万亿元、研发人员总量全球第一、优良天数占比达87.2%，这些硬核数据够亮眼！11篇报道，带你速览“十四五”期间中国奋进足迹，感受... 查看更多&gt;", "translation": "A quick look at China's strides during the 14th..."}}, {"title": "5. 9000亿元！央行发布重要公告", "value": "热度 7522214", "url": "https://www.baidu.com/s?wd=9000%E4%BA%BF%E5%85%83%EF%BC%81%E5%A4%AE%E8%A1%8C%E5%8F%91%E5%B8%83%E9%87%8D%E8%A6%81%E5%85%AC%E5%91%8A", "extra": {"rank": 5, "raw_score": "7522214", "api_source": "tianapi", "description": "10月24日，央行发布公告称，为保持银行体系流动性充裕，2025年10月27日（周一），中国人民银行将以固定数量、利率招标、多重价位中标方式开展90... 查看更多&gt;", "translation": "900 billion yuan! Central Bank issues important..."}}, {"title": "6. 蔚来卖爆了 开启“疯狂”招工模式", "value": "热度 7428803", "url": "https://www.baidu.com/s?wd=%E8%94%9A%E6%9D%A5%E5%8D%96%E7%88%86%E4%BA%86+%E5%BC%80%E5%90%AF%E2%80%9C%E7%96%AF%E7%8B%82%E2%80%9D%E6%8B%9B%E5%B7%A5%E6%A8%A1%E5%BC%8F", "extra": {"rank": 6, "raw_score": "7428803", "api_source": "tianapi", "description": "10月13日至19日，蔚来汽车单周交付量首次突破1.06万辆（蔚来品牌超4000辆、乐道超5000辆、萤火虫超1500辆），乐道L90单周交付量达3... 查看更多&gt;", "translation": "NIO's sales soar, launching a \"crazy\" hiring spree..."}}, {"title": "7. 网警起底无底线博流量网络乱象", "value": "热度 7332249", "url": "https://www.baidu.com/s?wd=%E7%BD%91%E8%AD%A6%E8%B5%B7%E5%BA%95%E6%97%A0%E5%BA%95%E7%BA%BF%E5%8D%9A%E6%B5%81%E9%87%8F%E7%BD%91%E7%BB%9C%E4%B9%B1%E8%B1%A1", "extra": {"rank": 7, "raw_score": "7332249", "api_source": "tianapi", "description": "近日，公安部公布了10起打击整治网络谣言典型案例。这些案例涉及的网络谣言，不仅损害公众的权益，也扰乱正常的社会公共秩序。其中四川德阳的案件，是有人移... 查看更多&gt;", "translation": "Cyber police expose the limitless pursuit of traffic..."}}, {"title": "8. 教育部：严禁将手机带入课堂", "value": "热度 7234182", "url": "https://www.baidu.com/s?wd=%E6%95%99%E8%82%B2%E9%83%A8%EF%BC%9A%E4%B8%A5%E7%A6%81%E5%B0%86%E6%89%8B%E6%9C%BA%E5%B8%A6%E5%85%A5%E8%AF%BE%E5%A0%82", "extra": {"rank": 8, "raw_score": "7234182", "api_source": "tianapi", "description": "10月24日，教育部印发《进一步加强中小学生心理健康工作十条措施》，明确严禁将手机等电子产品带入课堂，同时通过“息屏行动”减少网络依赖，并强化未成年... 查看更多&gt;", "translation": "Ministry of Education: Strictly prohibit bringing phones..."}}, {"title": "9. 高铁推出17元盒饭：门店现炒", "value": "热度 7137709", "url": "https://www.baidu.com/s?wd=%E9%AB%98%E9%93%81%E6%8E%A8%E5%87%BA17%E5%85%83%E7%9B%92%E9%A5%AD%EF%BC%9A%E9%97%A8%E5%BA%97%E7%8E%B0%E7%82%92", "extra": {"rank": 9, "raw_score": "7137709", "api_source": "tianapi", "description": "近日，中国铁路成都局集团在管内动车组列车上新推出两款平价套餐，包括川式小炒肉莽嘟嘟老式蛋炒饭和姜爆甜椒鸡丝莽嘟嘟老式蛋炒饭，定价17元，为旅客就餐增... 查看更多&gt;", "translation": "High-speed rail offers 17 yuan boxed meals, freshly made..."}}, {"title": "10. 央视公开台湾光复新闻影像", "value": "热度 7047985", "url": "https://www.baidu.com/s?wd=%E5%A4%AE%E8%A7%86%E5%85%AC%E5%BC%80%E5%8F%B0%E6%B9%BE%E5%85%89%E5%A4%8D%E6%96%B0%E9%97%BB%E5%BD%B1%E5%83%8F", "extra": {"rank": 10, "raw_score": "7047985", "api_source": "tianapi", "description": "近日，央视公开1945年台湾光复历史影像，展现10月25日台北中山堂受降仪式场景，日本代表签字投降后，民众街头庆祝“重获自由”。中国受降官宣告台湾及... 查看更多&gt;", "translation": "CCTV releases footage of Taiwan's liberation news..."}}]}