{"as_of": "2026-01-27T22:15:26+08:00", "source": "Baidu Top Realtime", "items": [{"title": "1. 习近平会见芬兰总理奥尔波", "value": "热度 7904583", "url": "https://www.baidu.com/s?wd=%E4%B9%A0%E8%BF%91%E5%B9%B3%E4%BC%9A%E8%A7%81%E8%8A%AC%E5%85%B0%E6%80%BB%E7%90%86%E5%A5%A5%E5%B0%94%E6%B3%A2", "extra": {"rank": 1, "raw_score": "7904583", "api_source": "tianapi", "description": "1月27日上午，国家主席习近平在北京人民大会堂会见来华进行正式访问的芬兰总理奥尔波。习近平指出，芬兰是最早同新中国建交的国家之一。建交76年来，无论... 查看更多&gt;", "translation": "Xi Jinping meets Finnish Prime Minister Orpo..."}}, {"title": "2. 大批中成药将退出市场", "value": "热度 7808232", "url": "https://www.baidu.com/s?wd=%E5%A4%A7%E6%89%B9%E4%B8%AD%E6%88%90%E8%8D%AF%E5%B0%86%E9%80%80%E5%87%BA%E5%B8%82%E5%9C%BA", "extra": {"rank": 2, "raw_score": "7808232", "api_source": "tianapi", "description": "大批中成药将退出市场。距离2026年7月1日仅剩半年时间，国家药监局《中药注册管理专门规定》第七十五条的落地进入最后窗口期。这意味着，国内现存约5.... 查看更多&gt;", "translation": "A large number of Chinese patent medicines will exit the..."}}, {"title": "3. 司机路遇“孤独婚车”主动为其开道", "value": "热度 7712402", "url": "https://www.baidu.com/s?wd=%E5%8F%B8%E6%9C%BA%E8%B7%AF%E9%81%87%E2%80%9C%E5%AD%A4%E7%8B%AC%E5%A9%9A%E8%BD%A6%E2%80%9D%E4%B8%BB%E5%8A%A8%E4%B8%BA%E5%85%B6%E5%BC%80%E9%81%93", "extra": {"rank": 3, "raw_score": "7712402", "api_source": "tianapi", "description": "近日，一大车司机在高速上，看到一辆“孤独”的婚车，司机：我来为你开道，祝远嫁的姑娘幸福。 查看更多&gt;", "translation": "Driver actively clears the way for a \"lonely wedding car\"..."}}, {"title": "4. 米兰冬奥会中国体育代表团成立", "value": "热度 7615856", "url": "https://www.baidu.com/s?wd=%E7%B1%B3%E5%85%B0%E5%86%AC%E5%A5%A5%E4%BC%9A%E4%B8%AD%E5%9B%BD%E4%BD%93%E8%82%B2%E4%BB%A3%E8%A1%A8%E5%9B%A2%E6%88%90%E7%AB%8B", "extra": {"rank": 4, "raw_score": "7615856", "api_source": "tianapi", "description": "1月27日上午，2026米兰冬奥会中国体育代表团在京成立。 查看更多&gt;", "translation": "China's sports delegation for the Milan Winter Olympics..."}}, {"title": "5. 中国汽车出口第一目的国易主", "value": "热度 7521113", "url": "https://www.baidu.com/s?wd=%E4%B8%AD%E5%9B%BD%E6%B1%BD%E8%BD%A6%E5%87%BA%E5%8F%A3%E7%AC%AC%E4%B8%80%E7%9B%AE%E7%9A%84%E5%9B%BD%E6%98%93%E4%B8%BB", "extra": {"rank": 5, "raw_score": "7521113", "api_source": "tianapi", "description": "近日，乘联分会秘书长崔东树最新披露的数据显示，2025年全年，中国对墨西哥汽车出口达到62.52万辆，较同期增长18.05万辆，成为中国的第一出口目... 查看更多&gt;", "translation": "China's top car export destination changes..."}}, {"title": "6. 中国情侣在巴厘岛患上“脏水病”", "value": "热度 7428817", "url": "https://www.baidu.com/s?wd=%E4%B8%AD%E5%9B%BD%E6%83%85%E4%BE%A3%E5%9C%A8%E5%B7%B4%E5%8E%98%E5%B2%9B%E6%82%A3%E4%B8%8A%E2%80%9C%E8%84%8F%E6%B0%B4%E7%97%85%E2%80%9D", "extra": {"rank": 6, "raw_score": "7428817", "api_source": "tianapi", "description": "近期多名游客在巴厘岛旅行后因患“脏水病”，引发广泛关注。游客Daisy在跨年旅行期间与男友均感染发病，症状类似肠胃炎，其男友病情严重，出现喷射性呕吐... 查看更多&gt;", "translation": "Chinese couple contracts \"dirty water disease\" in Bali..."}}, {"title": "7. 当《姑苏繁华图》遇见AI", "value": "热度 7332775", "url": "https://www.baidu.com/s?wd=%E5%BD%93%E3%80%8A%E5%A7%91%E8%8B%8F%E7%B9%81%E5%8D%8E%E5%9B%BE%E3%80%8B%E9%81%87%E8%A7%81AI", "extra": {"rank": 7, "raw_score": "7332775", "api_source": "tianapi", "description": "以清代宫廷画家徐扬笔下描绘苏州盛景的《姑苏繁华图》为蓝本，一场对话古今的苏州citywalk之旅就此展开。 查看更多&gt;", "translation": "When \"The Prosperous Suzhou\" Meets AI..."}}, {"title": "8. 研究发现午睡正悄悄拉开大脑年龄差", "value": "热度 7238031", "url": "https://www.baidu.com/s?wd=%E7%A0%94%E7%A9%B6%E5%8F%91%E7%8E%B0%E5%8D%88%E7%9D%A1%E6%AD%A3%E6%82%84%E6%82%84%E6%8B%89%E5%BC%80%E5%A4%A7%E8%84%91%E5%B9%B4%E9%BE%84%E5%B7%AE", "extra": {"rank": 8, "raw_score": "7238031", "api_source": "tianapi", "description": "最新科学研究告诉你：一次正确的午睡，能让你的大脑“深度重启”，效率翻倍，甚至延缓大脑的衰老！这也是很多人午睡后感觉自己神清气爽、下午工作效率翻倍的原... 查看更多&gt;", "translation": "Research finds napping quietly widens the brain age gap..."}}, {"title": "9. 多地对国企“近亲繁殖”出手了", "value": "热度 7140320", "url": "https://www.baidu.com/s?wd=%E5%A4%9A%E5%9C%B0%E5%AF%B9%E5%9B%BD%E4%BC%81%E2%80%9C%E8%BF%91%E4%BA%B2%E7%B9%81%E6%AE%96%E2%80%9D%E5%87%BA%E6%89%8B%E4%BA%86", "extra": {"rank": 9, "raw_score": "7140320", "api_source": "tianapi", "description": "过去一段时间，多个省份发起针对国企“近亲繁殖”的整治行动。此轮整治覆盖层级广泛，涉及县市区各级系统。所谓“近亲繁殖”，最早多见于巡视反馈中，用以形容... 查看更多&gt;", "translation": "Many places are taking action against \"nepotism\" in..."}}, {"title": "10. 澳大利亚气温逼近50摄氏度", "value": "热度 7047713", "url": "https://www.baidu.com/s?wd=%E6%BE%B3%E5%A4%A7%E5%88%A9%E4%BA%9A%E6%B0%94%E6%B8%A9%E9%80%BC%E8%BF%9150%E6%91%84%E6%B0%8F%E5%BA%A6", "extra": {"rank": 10, "raw_score": "7047713", "api_source": "tianapi", "description": "澳大利亚气象局27日发布警报说，该国东南部遭遇2009年以来最严重的热浪，南澳大利亚州一地气温达到49.6摄氏度，维多利亚州多地当日气温也创下该州纪... 查看更多&gt;", "translation": "Australia's temperatures approach 50 degrees Celsius..."}}]}