{"as_of": "2026-02-05T22:23:49+08:00", "source": "Baidu Top Realtime", "items": [{"title": "1. 做关键时顶得住的干部", "value": "热度 7904438", "url": "https://www.baidu.com/s?wd=%E5%81%9A%E5%85%B3%E9%94%AE%E6%97%B6%E9%A1%B6%E5%BE%97%E4%BD%8F%E7%9A%84%E5%B9%B2%E9%83%A8", "extra": {"rank": 1, "raw_score": "7904438", "api_source": "tianapi", "description": "“十五五”时期，我国发展处于战略机遇和风险挑战并存、不确定难预料因素增多的时期。爬坡过坎，一刻不能松劲，必须要有千千万万关键时顶得住的干部。面对新形... 查看更多&gt;", "translation": "A leader who can stand firm in critical moments..."}}, {"title": "2. 中国汽车将不再使用隐藏式车门把手", "value": "热度 7808700", "url": "https://www.baidu.com/s?wd=%E4%B8%AD%E5%9B%BD%E6%B1%BD%E8%BD%A6%E5%B0%86%E4%B8%8D%E5%86%8D%E4%BD%BF%E7%94%A8%E9%9A%90%E8%97%8F%E5%BC%8F%E8%BD%A6%E9%97%A8%E6%8A%8A%E6%89%8B", "extra": {"rank": 2, "raw_score": "7808700", "api_source": "tianapi", "description": "2月2日，强制性国家标准《汽车车门把手安全技术要求》由国家市场监督管理总局、国家标准化管理委员会批准发布，将于2027年1月1日起开始实施。新标准规... 查看更多&gt;", "translation": "Chinese cars will no longer use hidden door handles..."}}, {"title": "3. 周生生足金挂坠事件检测结果公布", "value": "热度 7713534", "url": "https://www.baidu.com/s?wd=%E5%91%A8%E7%94%9F%E7%94%9F%E8%B6%B3%E9%87%91%E6%8C%82%E5%9D%A0%E4%BA%8B%E4%BB%B6%E6%A3%80%E6%B5%8B%E7%BB%93%E6%9E%9C%E5%85%AC%E5%B8%83", "extra": {"rank": 3, "raw_score": "7713534", "api_source": "tianapi", "description": "据悉，“周生生挂坠金含量”官方检测完成：检测结果为足金，符合相关标准要求。目前，清远市清城区市场监督管理局已将检测报告送达消费者与商家，双方均表示对... 查看更多&gt;", "translation": "Zhou Sheng Sheng gold pendant incident test results..."}}, {"title": "4. 最珍贵的抵达不是远方而是回家", "value": "热度 7615839", "url": "https://www.baidu.com/s?wd=%E6%9C%80%E7%8F%8D%E8%B4%B5%E7%9A%84%E6%8A%B5%E8%BE%BE%E4%B8%8D%E6%98%AF%E8%BF%9C%E6%96%B9%E8%80%8C%E6%98%AF%E5%9B%9E%E5%AE%B6", "extra": {"rank": 4, "raw_score": "7615839", "api_source": "tianapi", "description": "在吉林省东南部，有一列穿行于崇山峻岭间的4245次绿皮火车，每天从通化站出发驶向长白山站，全程285公里，运行6小时03分，沿途停靠5个车站和8个乘... 查看更多&gt;", "translation": "The most precious arrival is not afar, but home..."}}, {"title": "5. 夺刀女警脸上伤疤无法恢复如初", "value": "热度 7520237", "url": "https://www.baidu.com/s?wd=%E5%A4%BA%E5%88%80%E5%A5%B3%E8%AD%A6%E8%84%B8%E4%B8%8A%E4%BC%A4%E7%96%A4%E6%97%A0%E6%B3%95%E6%81%A2%E5%A4%8D%E5%A6%82%E5%88%9D", "extra": {"rank": 5, "raw_score": "7520237", "api_source": "tianapi", "description": "2月4日，休假时赤手空拳夺刀救人的河南女警王妙丽被授予全国司法行政系统一级英模。她救人时面部受创缝30多针，伤疤虽无法恢复如初，却被她视作警察使命的... 查看更多&gt;", "translation": "The scar on the female officer's face cannot fully heal..."}}, {"title": "6. 人民日报评小洛熙事件", "value": "热度 7424275", "url": "https://www.baidu.com/s?wd=%E4%BA%BA%E6%B0%91%E6%97%A5%E6%8A%A5%E8%AF%84%E5%B0%8F%E6%B4%9B%E7%86%99%E4%BA%8B%E4%BB%B6", "extra": {"rank": 6, "raw_score": "7424275", "api_source": "tianapi", "description": "2月5日，浙江宁波调查组公布了小洛熙事件的最新通报，以权威详实的调查核查还原了事件发生的来龙去脉，厘清了造成这起悲剧发生的责任和过错，回应了社会舆论... 查看更多&gt;", "translation": "People's Daily comments on the Xiao Luoxi incident..."}}, {"title": "7. 博主摆拍“孩子险被拐走”被罚", "value": "热度 7334133", "url": "https://www.baidu.com/s?wd=%E5%8D%9A%E4%B8%BB%E6%91%86%E6%8B%8D%E2%80%9C%E5%AD%A9%E5%AD%90%E9%99%A9%E8%A2%AB%E6%8B%90%E8%B5%B0%E2%80%9D%E8%A2%AB%E7%BD%9A", "extra": {"rank": 7, "raw_score": "7334133", "api_source": "tianapi", "description": "近日，四川泸州一博主发布虚假视频称“自家孩子险被拐走”，造成属地居民恐慌。经警方调查确认系摆拍，孩子实际由家人安全接离。目前，属地公安机关已依法对涉... 查看更多&gt;", "translation": "Blogger fined for staged \"child nearly abducted\" photo..."}}, {"title": "8. 女孩喂大鹅遭袭击当场霸气还击", "value": "热度 7236742", "url": "https://www.baidu.com/s?wd=%E5%A5%B3%E5%AD%A9%E5%96%82%E5%A4%A7%E9%B9%85%E9%81%AD%E8%A2%AD%E5%87%BB%E5%BD%93%E5%9C%BA%E9%9C%B8%E6%B0%94%E8%BF%98%E5%87%BB", "extra": {"rank": 8, "raw_score": "7236742", "api_source": "tianapi", "description": "2月5日，山东烟台，一女孩喂大鹅遭攻击。随后女孩当场反击，手握鹅脖子，一顿脚踢，直接打服，大鹅乖乖去吃食了。妈妈：我每次喂鹅都躲着走，女儿看似文静，... 查看更多&gt;", "translation": "Girl feeding a goose is attacked but fights back fiercely..."}}, {"title": "9. 云南男子从起火车中救3人：实为过错方", "value": "热度 7143726", "url": "https://www.baidu.com/s?wd=%E4%BA%91%E5%8D%97%E7%94%B7%E5%AD%90%E4%BB%8E%E8%B5%B7%E7%81%AB%E8%BD%A6%E4%B8%AD%E6%95%913%E4%BA%BA%EF%BC%9A%E5%AE%9E%E4%B8%BA%E8%BF%87%E9%94%99%E6%96%B9", "extra": {"rank": 9, "raw_score": "7143726", "api_source": "tianapi", "description": "2月4日，云南一网友发布的“从起火车辆中救出3人”的视频引发广泛关注，白衣货车司机从起火网约车中救出3人，却遗憾未能救出副驾人员且自身被烧伤。5日文... 查看更多&gt;", "translation": "Yunnan man saves 3 from burning train: actually at fault..."}}, {"title": "10. A股春节休市安排来了", "value": "热度 7040477", "url": "https://www.baidu.com/s?wd=A%E8%82%A1%E6%98%A5%E8%8A%82%E4%BC%91%E5%B8%82%E5%AE%89%E6%8E%92%E6%9D%A5%E4%BA%86", "extra": {"rank": 10, "raw_score": "7040477", "api_source": "tianapi", "description": "2月5日，沪深北交易所公布2026年春节休市安排：2月15日至2月23日休市，2月24日起照常开市。另外，2月14日、2月28日为周末休市。 查看更多&gt;", "translation": "A-shares holiday schedule for the Spring Festival is here..."}}]}