{"as_of": "2026-05-04T11:45:28+08:00", "source": "Baidu Top Realtime", "items": [{"title": "1. 奋斗是青春最亮丽的底色", "value": "热度 7904205", "url": "https://www.baidu.com/s?wd=%E5%A5%8B%E6%96%97%E6%98%AF%E9%9D%92%E6%98%A5%E6%9C%80%E4%BA%AE%E4%B8%BD%E7%9A%84%E5%BA%95%E8%89%B2", "extra": {"rank": 1, "raw_score": "7904205", "api_source": "tianapi", "description": "对于广大青年朋友，习近平总书记饱含期许，他寄语青年“青春由磨砺而出彩，人生因奋斗而升华”“奋斗是青春最亮丽的底色”。“五四”青年节到来之际，让我们重... 查看更多&gt;", "translation": ""}}, {"title": "2. 获奖名单上 他的名字被加上了方框", "value": "热度 7807918", "url": "https://www.baidu.com/s?wd=%E8%8E%B7%E5%A5%96%E5%90%8D%E5%8D%95%E4%B8%8A+%E4%BB%96%E7%9A%84%E5%90%8D%E5%AD%97%E8%A2%AB%E5%8A%A0%E4%B8%8A%E4%BA%86%E6%96%B9%E6%A1%86", "extra": {"rank": 2, "raw_score": "7807918", "api_source": "tianapi", "description": "近日，辽宁中医药大学基础医学院2022级中西医临床医学专业本科生金城龙，被追授中国青年五四奖章。金城龙的名字，也是名单中唯一一个被方框特别标注的名字... 查看更多&gt;", "translation": ""}}, {"title": "3. 大西洋一邮轮出现病毒感染 已致3死", "value": "热度 7714121", "url": "https://www.baidu.com/s?wd=%E5%A4%A7%E8%A5%BF%E6%B4%8B%E4%B8%80%E9%82%AE%E8%BD%AE%E5%87%BA%E7%8E%B0%E7%97%85%E6%AF%92%E6%84%9F%E6%9F%93+%E5%B7%B2%E8%87%B43%E6%AD%BB", "extra": {"rank": 3, "raw_score": "7714121", "api_source": "tianapi", "description": "当地时间5月3日晚，世界卫生组织证实，一艘在大西洋上航行的邮轮出现汉坦病毒感染，迄今为止，已确诊一例汉坦病毒感染病例，另有5例疑似病例。6名患者中，... 查看更多&gt;", "translation": ""}}, {"title": "4. 中国青年好young的", "value": "热度 7619094", "url": "https://www.baidu.com/s?wd=%E4%B8%AD%E5%9B%BD%E9%9D%92%E5%B9%B4%E5%A5%BDyoung%E7%9A%84", "extra": {"rank": 4, "raw_score": "7619094", "api_source": "tianapi", "description": "青春有多少种模样，就有多少种光芒！青春是勇气，是力量，是敢于追梦，是一往无前。青春属于年轻人，更属于奋斗者。愿我们永远朝气蓬勃，一路逐梦前行！致敬奋... 查看更多&gt;", "translation": ""}}, {"title": "5. 保时捷在华坚持不降价不国产", "value": "热度 7521158", "url": "https://www.baidu.com/s?wd=%E4%BF%9D%E6%97%B6%E6%8D%B7%E5%9C%A8%E5%8D%8E%E5%9D%9A%E6%8C%81%E4%B8%8D%E9%99%8D%E4%BB%B7%E4%B8%8D%E5%9B%BD%E4%BA%A7", "extra": {"rank": 5, "raw_score": "7521158", "api_source": "tianapi", "description": "近日，保时捷CFO白禹翰强调：“我们不会参与中国市场过于激烈的价格竞争，否则将侵蚀高端品牌形象和利润根基。”此外，保时捷再次重申不会在中国国产。 查看更多&gt;", "translation": ""}}, {"title": "6. 买三文鱼套餐吃到虹鳟食客起诉餐厅", "value": "热度 7427437", "url": "https://www.baidu.com/s?wd=%E4%B9%B0%E4%B8%89%E6%96%87%E9%B1%BC%E5%A5%97%E9%A4%90%E5%90%83%E5%88%B0%E8%99%B9%E9%B3%9F%E9%A3%9F%E5%AE%A2%E8%B5%B7%E8%AF%89%E9%A4%90%E5%8E%85", "extra": {"rank": 6, "raw_score": "7427437", "api_source": "tianapi", "description": "近日，网名为“小鸟”的消费者在郑州一家自助餐厅买了三文鱼畅吃套餐，用餐过程中发现口感不对，店家表示店内提供的三文鱼刺身原材料为虹鳟。5月3日，消费者... 查看更多&gt;", "translation": ""}}, {"title": "7. 日本几乎已无巢鸭监狱痕迹", "value": "热度 7328363", "url": "https://www.baidu.com/s?wd=%E6%97%A5%E6%9C%AC%E5%87%A0%E4%B9%8E%E5%B7%B2%E6%97%A0%E5%B7%A2%E9%B8%AD%E7%9B%91%E7%8B%B1%E7%97%95%E8%BF%B9", "extra": {"rank": 7, "raw_score": "7328363", "api_source": "tianapi", "description": "1978年，曾用于追究战争责任的巢鸭监狱原址上建成摩天大楼，成了东京核心商业地标之一。今天的东池袋中央公园几无巢鸭监狱痕迹，只有公园角落立着的一块小... 查看更多&gt;", "translation": ""}}, {"title": "8. 莫雷加德回应赢中国男团：具历史意义", "value": "热度 7233553", "url": "https://www.baidu.com/s?wd=%E8%8E%AB%E9%9B%B7%E5%8A%A0%E5%BE%B7%E5%9B%9E%E5%BA%94%E8%B5%A2%E4%B8%AD%E5%9B%BD%E7%94%B7%E5%9B%A2%EF%BC%9A%E5%85%B7%E5%8E%86%E5%8F%B2%E6%84%8F%E4%B9%89", "extra": {"rank": 8, "raw_score": "7233553", "api_source": "tianapi", "description": "5月3日，瑞典队在2026伦敦世乒赛男团比赛中以3-2击败中国队，瑞典选手莫雷加德赛后表示，这场胜利具有历史意义，是瑞典队时隔26年再度战胜国乒，并... 查看更多&gt;", "translation": ""}}, {"title": "9. 领舞的“法拉利大叔”火了", "value": "热度 7135813", "url": "https://www.baidu.com/s?wd=%E9%A2%86%E8%88%9E%E7%9A%84%E2%80%9C%E6%B3%95%E6%8B%89%E5%88%A9%E5%A4%A7%E5%8F%94%E2%80%9D%E7%81%AB%E4%BA%86", "extra": {"rank": 9, "raw_score": "7135813", "api_source": "tianapi", "description": "近日，一段“北京体育大会上数十位裁判齐跳舞蹈”的视频在全网刷屏。视频里，一位气质出众、舞步潇洒的“大叔”一出场就抓住所有人目光，网友纷纷称赞他气场强... 查看更多&gt;", "translation": ""}}, {"title": "10. 中国队夺得第12个汤姆斯杯冠军", "value": "热度 7045592", "url": "https://www.baidu.com/s?wd=%E4%B8%AD%E5%9B%BD%E9%98%9F%E5%A4%BA%E5%BE%97%E7%AC%AC12%E4%B8%AA%E6%B1%A4%E5%A7%86%E6%96%AF%E6%9D%AF%E5%86%A0%E5%86%9B", "extra": {"rank": 10, "raw_score": "7045592", "api_source": "tianapi", "description": "北京时间5月4日，2026汤姆斯杯世界男子羽毛球团体锦标赛决赛，中国队3-1战胜法国队，中国队夺得第12个汤姆斯杯冠军。 查看更多&gt;", "translation": ""}}]}