{"as_of": "2025-09-23T19:40:00+08:00", "source": "Yahoo Finance (Sample)", "items": [{"title": "USD/CNY", "value": 7.2345, "url": "https://finance.yahoo.com/quote/CNY=X", "extra": {"symbol": "CNY=X", "chg_pct": 0.12, "ts": 1695462000}}, {"title": "USD/CNH", "value": 7.2567, "url": "https://finance.yahoo.com/quote/CNH=X", "extra": {"symbol": "CNH=X", "chg_pct": -0.08, "ts": 1695462000}}, {"title": "EUR/CNY", "value": 7.8901, "url": "https://finance.yahoo.com/quote/EURCNY=X", "extra": {"symbol": "EURCNY=X", "chg_pct": 0.34, "ts": 1695462000}}]}