{"schema_version": 1, "as_of": "2026-06-11T11:47:06+08:00", "source": "Yahoo Finance (fallback)", "items": [{"title": "USD/CNY", "value": 6.7738, "url": "https://finance.yahoo.com/quote/CNY=X", "extra": {"symbol": "CNY=X", "chg_pct": -0.0029524653085388555, "ts": 1781149610}}, {"title": "USD/CNH", "value": 6.7763, "url": "https://finance.yahoo.com/quote/CNH=X", "extra": {"symbol": "CNH=X", "chg_pct": -0.025081144880489688, "ts": 1781149622}}, {"title": "EUR/CNY", "value": 7.8211, "url": "https://finance.yahoo.com/quote/EURCNY=X", "extra": {"symbol": "EURCNY=X", "chg_pct": 0.08958165367733406, "ts": 1781149448}}, {"title": "JPY/CNY", "value": 0.0421, "url": "https://finance.yahoo.com/quote/JPYCNY=X", "extra": {"symbol": "JPYCNY=X", "chg_pct": 0.0, "ts": 1781149448}}]}