{"as_of": "2026-04-13T19:01:38+08:00", "source": "Yahoo Finance (fallback)", "items": [{"title": "USD/CNY", "value": 6.8312, "url": "https://finance.yahoo.com/quote/CNY=X", "extra": {"symbol": "CNY=X", "chg_pct": 0.057123606696641314, "ts": 1776078074}}, {"title": "USD/CNH", "value": 6.8307, "url": "https://finance.yahoo.com/quote/CNH=X", "extra": {"symbol": "CNH=X", "chg_pct": 0.14954915328788518, "ts": 1776078097}}, {"title": "EUR/CNY", "value": 7.9869, "url": "https://finance.yahoo.com/quote/EURCNY=X", "extra": {"symbol": "EURCNY=X", "chg_pct": -0.21364317841078498, "ts": 1776077941}}, {"title": "JPY/CNY", "value": 0.0427, "url": "https://finance.yahoo.com/quote/JPYCNY=X", "extra": {"symbol": "JPYCNY=X", "chg_pct": -0.2336448598130746, "ts": 1776077941}}]}