{"as_of": "2026-01-28T18:43:27+08:00", "source": "Yahoo Finance (fallback)", "items": [{"title": "USD/CNY", "value": 6.9457, "url": "https://finance.yahoo.com/quote/CNY=X", "extra": {"symbol": "CNY=X", "chg_pct": -0.11935576646533375, "ts": 1769594823}}, {"title": "USD/CNH", "value": 6.9415, "url": "https://finance.yahoo.com/quote/CNH=X", "extra": {"symbol": "CNH=X", "chg_pct": 0.1298232960692312, "ts": 1769597006}}, {"title": "EUR/CNY", "value": 8.3203, "url": "https://finance.yahoo.com/quote/EURCNY=X", "extra": {"symbol": "EURCNY=X", "chg_pct": -0.6127860862917629, "ts": 1769596554}}, {"title": "JPY/CNY", "value": 0.0454, "url": "https://finance.yahoo.com/quote/JPYCNY=X", "extra": {"symbol": "JPYCNY=X", "chg_pct": -0.43859649122806754, "ts": 1769596554}}]}