{"as_of": "2026-04-29T14:43:33+08:00", "source": "Yahoo Finance (fallback)", "items": [{"title": "USD/CNY", "value": 6.8328, "url": "https://finance.yahoo.com/quote/CNY=X", "extra": {"symbol": "CNY=X", "chg_pct": -0.059968699264289584, "ts": 1777444988}}, {"title": "USD/CNH", "value": 6.8353, "url": "https://finance.yahoo.com/quote/CNH=X", "extra": {"symbol": "CNH=X", "chg_pct": -0.04240882103476732, "ts": 1777445012}}, {"title": "EUR/CNY", "value": 7.9958, "url": "https://finance.yahoo.com/quote/EURCNY=X", "extra": {"symbol": "EURCNY=X", "chg_pct": -0.15359448558335487, "ts": 1777444764}}, {"title": "JPY/CNY", "value": 0.0428, "url": "https://finance.yahoo.com/quote/JPYCNY=X", "extra": {"symbol": "JPYCNY=X", "chg_pct": 0.0, "ts": 1777444764}}]}