{"as_of": "2025-09-25T14:03:47+08:00", "source": "Yahoo Finance (fallback)", "items": [{"title": "USD/CNY", "value": 7.1236, "url": "https://finance.yahoo.com/quote/CNY=X", "extra": {"symbol": "CNY=X", "chg_pct": -0.1037722619548523, "ts": 1758780197}}, {"title": "USD/CNH", "value": 7.1308, "url": "https://finance.yahoo.com/quote/CNH=X", "extra": {"symbol": "CNH=X", "chg_pct": -0.07006922839765539, "ts": 1758780226}}, {"title": "EUR/CNY", "value": 8.364, "url": "https://finance.yahoo.com/quote/EURCNY=X", "extra": {"symbol": "EURCNY=X", "chg_pct": -0.07884739445199662, "ts": 1758779928}}, {"title": "JPY/CNY", "value": 0.0478, "url": "https://finance.yahoo.com/quote/JPYCNY=X", "extra": {"symbol": "JPYCNY=X", "chg_pct": -0.20876826722337358, "ts": 1758779928}}]}