{"as_of": "2026-04-06T06:06:04+08:00", "source": "Yahoo Finance (fallback)", "items": [{"title": "USD/CNY", "value": 6.8819, "url": "https://finance.yahoo.com/quote/CNY=X", "extra": {"symbol": "CNY=X", "chg_pct": -0.0464771753496759, "ts": 1775414674}}, {"title": "USD/CNH", "value": 6.8846, "url": "https://finance.yahoo.com/quote/CNH=X", "extra": {"symbol": "CNH=X", "chg_pct": -0.04065394778872404, "ts": 1775249951}}, {"title": "EUR/CNY", "value": 7.9276, "url": "https://finance.yahoo.com/quote/EURCNY=X", "extra": {"symbol": "EURCNY=X", "chg_pct": -0.18257136021958875, "ts": 1775416256}}, {"title": "JPY/CNY", "value": 0.043, "url": "https://finance.yahoo.com/quote/JPYCNY=X", "extra": {"symbol": "JPYCNY=X", "chg_pct": -0.23201856148492547, "ts": 1775251556}}]}