{"as_of": "2026-03-04T14:09:39+08:00", "source": "Yahoo Finance (fallback)", "items": [{"title": "SSE Composite", "value": 4078.536, "url": "https://finance.yahoo.com/quote/000001.SS", "extra": {"symbol": "000001.SS", "chg_pct": -2.4877886668308413, "ts": 1772603665}}, {"title": "Shenzhen Component", "value": 13933.513, "url": "https://finance.yahoo.com/quote/399001.SZ", "extra": {"symbol": "399001.SZ", "chg_pct": -3.679623664090465, "ts": 1772603677}}, {"title": "ChiNext", "value": 3169.744, "url": "https://finance.yahoo.com/quote/399006.SZ", "extra": {"symbol": "399006.SZ", "chg_pct": -1.2381437253737466, "ts": 1772603677}}, {"title": "STAR 50", "value": 1384.2388, "url": "https://finance.yahoo.com/quote/000688.SS", "extra": {"symbol": "000688.SS", "chg_pct": -0.30039408402203366, "ts": 1772603665}}]}