{"as_of": "2026-01-26T11:16:33+08:00", "source": "Yahoo Finance (fallback)", "items": [{"title": "SSE Composite", "value": 4125.199, "url": "https://finance.yahoo.com/quote/000001.SS", "extra": {"symbol": "000001.SS", "chg_pct": -0.26510070683851383, "ts": 1769396485}}, {"title": "Shenzhen Component", "value": 14281.598, "url": "https://finance.yahoo.com/quote/399001.SZ", "extra": {"symbol": "399001.SZ", "chg_pct": -1.0946242632616332, "ts": 1769396491}}, {"title": "ChiNext", "value": 3304.3557, "url": "https://finance.yahoo.com/quote/399006.SZ", "extra": {"symbol": "399006.SZ", "chg_pct": -1.3478923472655673, "ts": 1769396491}}, {"title": "STAR 50", "value": 1531.5181, "url": "https://finance.yahoo.com/quote/000688.SS", "extra": {"symbol": "000688.SS", "chg_pct": -1.4281454428385596, "ts": 1769396485}}]}