{"as_of": "2026-05-13T06:26:21+08:00", "source": "Yahoo Finance (fallback)", "items": [{"title": "SSE Composite", "value": 4214.489, "url": "https://finance.yahoo.com/quote/000001.SS", "extra": {"symbol": "000001.SS", "chg_pct": 0.8263017500209277, "ts": 1778569234}}, {"title": "Shenzhen Component", "value": 15824.921, "url": "https://finance.yahoo.com/quote/399001.SZ", "extra": {"symbol": "399001.SZ", "chg_pct": 1.6777457947288004, "ts": 1778574580}}, {"title": "ChiNext", "value": 3934.882, "url": "https://finance.yahoo.com/quote/399006.SZ", "extra": {"symbol": "399006.SZ", "chg_pct": 0.15037259473777884, "ts": 1778574595}}, {"title": "STAR 50", "value": 1723.7836, "url": "https://finance.yahoo.com/quote/000688.SS", "extra": {"symbol": "000688.SS", "chg_pct": 0.4131319117693517, "ts": 1778569234}}]}