{"as_of": "2026-05-04T19:12:34+08:00", "source": "Tencent WeChat Hot Topics", "items": [{"title": "1. 以实现中华民族伟大复兴为己任", "value": "指数 7904673", "url": "https://weixin.sogou.com/weixin?type=2&query=%E4%BB%A5%E5%AE%9E%E7%8E%B0%E4%B8%AD%E5%8D%8E%E6%B0%91%E6%97%8F%E4%BC%9F%E5%A4%A7%E5%A4%8D%E5%85%B4%E4%B8%BA%E5%B7%B1%E4%BB%BB", "extra": {"rank": 1, "raw_score": "7904673", "api_source": "tianapi", "translation": ""}}, {"title": "2. 敦煌鸣沙山坐满游客挤成“拼豆”", "value": "指数 7809077", "url": "https://weixin.sogou.com/weixin?type=2&query=%E6%95%A6%E7%85%8C%E9%B8%A3%E6%B2%99%E5%B1%B1%E5%9D%90%E6%BB%A1%E6%B8%B8%E5%AE%A2%E6%8C%A4%E6%88%90%E2%80%9C%E6%8B%BC%E8%B1%86%E2%80%9D", "extra": {"rank": 2, "raw_score": "7809077", "api_source": "tianapi", "translation": ""}}, {"title": "3. 藏族男孩天安门前唱歌刷屏全网", "value": "指数 7713994", "url": "https://weixin.sogou.com/weixin?type=2&query=%E8%97%8F%E6%97%8F%E7%94%B7%E5%AD%A9%E5%A4%A9%E5%AE%89%E9%97%A8%E5%89%8D%E5%94%B1%E6%AD%8C%E5%88%B7%E5%B1%8F%E5%85%A8%E7%BD%91", "extra": {"rank": 3, "raw_score": "7713994", "api_source": "tianapi", "translation": ""}}, {"title": "4. 返程开启 这份出行指南请收好", "value": "指数 7619396", "url": "https://weixin.sogou.com/weixin?type=2&query=%E8%BF%94%E7%A8%8B%E5%BC%80%E5%90%AF+%E8%BF%99%E4%BB%BD%E5%87%BA%E8%A1%8C%E6%8C%87%E5%8D%97%E8%AF%B7%E6%94%B6%E5%A5%BD", "extra": {"rank": 4, "raw_score": "7619396", "api_source": "tianapi", "translation": ""}}, {"title": "5. 辽宁发生交通事故已造成8人死亡", "value": "指数 7520363", "url": "https://weixin.sogou.com/weixin?type=2&query=%E8%BE%BD%E5%AE%81%E5%8F%91%E7%94%9F%E4%BA%A4%E9%80%9A%E4%BA%8B%E6%95%85%E5%B7%B2%E9%80%A0%E6%88%908%E4%BA%BA%E6%AD%BB%E4%BA%A1", "extra": {"rank": 5, "raw_score": "7520363", "api_source": "tianapi", "translation": ""}}, {"title": "6. 广州有人花300多买了28斤榴莲", "value": "指数 7424275", "url": "https://weixin.sogou.com/weixin?type=2&query=%E5%B9%BF%E5%B7%9E%E6%9C%89%E4%BA%BA%E8%8A%B1300%E5%A4%9A%E4%B9%B0%E4%BA%8628%E6%96%A4%E6%A6%B4%E8%8E%B2", "extra": {"rank": 6, "raw_score": "7424275", "api_source": "tianapi", "translation": ""}}, {"title": "7. 伊朗向美军舰发射导弹", "value": "指数 7331818", "url": "https://weixin.sogou.com/weixin?type=2&query=%E4%BC%8A%E6%9C%97%E5%90%91%E7%BE%8E%E5%86%9B%E8%88%B0%E5%8F%91%E5%B0%84%E5%AF%BC%E5%BC%B9", "extra": {"rank": 7, "raw_score": "7331818", "api_source": "tianapi", "translation": ""}}, {"title": "8. 曾经爆火的高端牛奶不被买账了", "value": "指数 7234764", "url": "https://weixin.sogou.com/weixin?type=2&query=%E6%9B%BE%E7%BB%8F%E7%88%86%E7%81%AB%E7%9A%84%E9%AB%98%E7%AB%AF%E7%89%9B%E5%A5%B6%E4%B8%8D%E8%A2%AB%E4%B9%B0%E8%B4%A6%E4%BA%86", "extra": {"rank": 8, "raw_score": "7234764", "api_source": "tianapi", "translation": ""}}, {"title": "9. 329元一晚的酒店像捅了蟑螂窝", "value": "指数 7141917", "url": "https://weixin.sogou.com/weixin?type=2&query=329%E5%85%83%E4%B8%80%E6%99%9A%E7%9A%84%E9%85%92%E5%BA%97%E5%83%8F%E6%8D%85%E4%BA%86%E8%9F%91%E8%9E%82%E7%AA%9D", "extra": {"rank": 9, "raw_score": "7141917", "api_source": "tianapi", "translation": ""}}, {"title": "10. 商场不倒翁演员从约3米高处摔落", "value": "指数 7046762", "url": "https://weixin.sogou.com/weixin?type=2&query=%E5%95%86%E5%9C%BA%E4%B8%8D%E5%80%92%E7%BF%81%E6%BC%94%E5%91%98%E4%BB%8E%E7%BA%A63%E7%B1%B3%E9%AB%98%E5%A4%84%E6%91%94%E8%90%BD", "extra": {"rank": 10, "raw_score": "7046762", "api_source": "tianapi", "translation": ""}}]}