{"as_of": "2026-02-07T14:08:33+08:00", "source": "Tencent WeChat Hot Topics", "items": [{"title": "1. 中国体育逐梦正当时", "value": "指数 7904768", "url": "https://weixin.sogou.com/weixin?type=2&query=%E4%B8%AD%E5%9B%BD%E4%BD%93%E8%82%B2%E9%80%90%E6%A2%A6%E6%AD%A3%E5%BD%93%E6%97%B6", "extra": {"rank": 1, "raw_score": "7904768", "api_source": "tianapi", "translation": "Chinese sports are on the rise..."}}, {"title": "2. 东部战区 记者紧张得不关摄像机", "value": "指数 7808821", "url": "https://weixin.sogou.com/weixin?type=2&query=%E4%B8%9C%E9%83%A8%E6%88%98%E5%8C%BA+%E8%AE%B0%E8%80%85%E7%B4%A7%E5%BC%A0%E5%BE%97%E4%B8%8D%E5%85%B3%E6%91%84%E5%83%8F%E6%9C%BA", "extra": {"rank": 2, "raw_score": "7808821", "api_source": "tianapi", "translation": "Eastern Theater Command reporter nervously forgot to..."}}, {"title": "3. 汽车飞机二合一！国内首款首飞成功", "value": "指数 7713548", "url": "https://weixin.sogou.com/weixin?type=2&query=%E6%B1%BD%E8%BD%A6%E9%A3%9E%E6%9C%BA%E4%BA%8C%E5%90%88%E4%B8%80%EF%BC%81%E5%9B%BD%E5%86%85%E9%A6%96%E6%AC%BE%E9%A6%96%E9%A3%9E%E6%88%90%E5%8A%9F", "extra": {"rank": 3, "raw_score": "7713548", "api_source": "tianapi", "translation": "Car and plane in one! China's first successful test..."}}, {"title": "4. 首款首个首次 我国多领域解锁新成就", "value": "指数 7616244", "url": "https://weixin.sogou.com/weixin?type=2&query=%E9%A6%96%E6%AC%BE%E9%A6%96%E4%B8%AA%E9%A6%96%E6%AC%A1+%E6%88%91%E5%9B%BD%E5%A4%9A%E9%A2%86%E5%9F%9F%E8%A7%A3%E9%94%81%E6%96%B0%E6%88%90%E5%B0%B1", "extra": {"rank": 4, "raw_score": "7616244", "api_source": "tianapi", "translation": "China unlocks new achievements in multiple fields..."}}, {"title": "5. 上海人大代表谈为何总打到“臭车”", "value": "指数 7522910", "url": "https://weixin.sogou.com/weixin?type=2&query=%E4%B8%8A%E6%B5%B7%E4%BA%BA%E5%A4%A7%E4%BB%A3%E8%A1%A8%E8%B0%88%E4%B8%BA%E4%BD%95%E6%80%BB%E6%89%93%E5%88%B0%E2%80%9C%E8%87%AD%E8%BD%A6%E2%80%9D", "extra": {"rank": 5, "raw_score": "7522910", "api_source": "tianapi", "translation": "Shanghai representatives discuss why they target \"smelly..."}}, {"title": "6. 第一批被草莓“报复”的网友出现了", "value": "指数 7426240", "url": "https://weixin.sogou.com/weixin?type=2&query=%E7%AC%AC%E4%B8%80%E6%89%B9%E8%A2%AB%E8%8D%89%E8%8E%93%E2%80%9C%E6%8A%A5%E5%A4%8D%E2%80%9D%E7%9A%84%E7%BD%91%E5%8F%8B%E5%87%BA%E7%8E%B0%E4%BA%86", "extra": {"rank": 6, "raw_score": "7426240", "api_source": "tianapi", "translation": "The first batch of netizens \"retaliated\" by strawberries..."}}, {"title": "7. 一趟航班3个同款行李箱3位箱主全拿错", "value": "指数 7328604", "url": "https://weixin.sogou.com/weixin?type=2&query=%E4%B8%80%E8%B6%9F%E8%88%AA%E7%8F%AD3%E4%B8%AA%E5%90%8C%E6%AC%BE%E8%A1%8C%E6%9D%8E%E7%AE%B13%E4%BD%8D%E7%AE%B1%E4%B8%BB%E5%85%A8%E6%8B%BF%E9%94%99", "extra": {"rank": 7, "raw_score": "7328604", "api_source": "tianapi", "translation": "Three passengers took the wrong identical suitcases on a..."}}, {"title": "8. 米兰冬奥会金牌或成历史最贵", "value": "指数 7234852", "url": "https://weixin.sogou.com/weixin?type=2&query=%E7%B1%B3%E5%85%B0%E5%86%AC%E5%A5%A5%E4%BC%9A%E9%87%91%E7%89%8C%E6%88%96%E6%88%90%E5%8E%86%E5%8F%B2%E6%9C%80%E8%B4%B5", "extra": {"rank": 8, "raw_score": "7234852", "api_source": "tianapi", "translation": "Milan Winter Olympics gold medal may be the most..."}}, {"title": "9. 29元韭菜炒蚌壳肉吃出粉色珍珠", "value": "指数 7139518", "url": "https://weixin.sogou.com/weixin?type=2&query=29%E5%85%83%E9%9F%AD%E8%8F%9C%E7%82%92%E8%9A%8C%E5%A3%B3%E8%82%89%E5%90%83%E5%87%BA%E7%B2%89%E8%89%B2%E7%8F%8D%E7%8F%A0", "extra": {"rank": 9, "raw_score": "7139518", "api_source": "tianapi", "translation": "29 yuan stir-fried chives with clam meat yielded pink..."}}, {"title": "10. 博主发小米极氪对撞测试视频被捕", "value": "指数 7046498", "url": "https://weixin.sogou.com/weixin?type=2&query=%E5%8D%9A%E4%B8%BB%E5%8F%91%E5%B0%8F%E7%B1%B3%E6%9E%81%E6%B0%AA%E5%AF%B9%E6%92%9E%E6%B5%8B%E8%AF%95%E8%A7%86%E9%A2%91%E8%A2%AB%E6%8D%95", "extra": {"rank": 10, "raw_score": "7046498", "api_source": "tianapi", "translation": "Blogger arrested for posting video of Xiaomi crash test..."}}]}