{"as_of": "2025-10-09T10:53:01+08:00", "source": "Tencent WeChat Hot Topics", "items": [{"title": "1. 古树情缘", "value": "指数 7904430", "url": "https://weixin.sogou.com/weixin?type=2&query=%E5%8F%A4%E6%A0%91%E6%83%85%E7%BC%98", "extra": {"rank": 1, "raw_score": "7904430", "api_source": "tianapi", "translation": "The Affection of Ancient Trees..."}}, {"title": "2. 10年来首次！沪指突破3900点", "value": "指数 7808219", "url": "https://weixin.sogou.com/weixin?type=2&query=10%E5%B9%B4%E6%9D%A5%E9%A6%96%E6%AC%A1%EF%BC%81%E6%B2%AA%E6%8C%87%E7%AA%81%E7%A0%B43900%E7%82%B9", "extra": {"rank": 2, "raw_score": "7808219", "api_source": "tianapi", "translation": "First time in 10 years! Shanghai index surpasses 3900..."}}, {"title": "3. 高速免费结束前收费站人员高喊快点", "value": "指数 7712891", "url": "https://weixin.sogou.com/weixin?type=2&query=%E9%AB%98%E9%80%9F%E5%85%8D%E8%B4%B9%E7%BB%93%E6%9D%9F%E5%89%8D%E6%94%B6%E8%B4%B9%E7%AB%99%E4%BA%BA%E5%91%98%E9%AB%98%E5%96%8A%E5%BF%AB%E7%82%B9", "extra": {"rank": 3, "raw_score": "7712891", "api_source": "tianapi", "translation": "Toll booth staff shouted to hurry before free highway..."}}, {"title": "4. 中国航天 生日快乐", "value": "指数 7616598", "url": "https://weixin.sogou.com/weixin?type=2&query=%E4%B8%AD%E5%9B%BD%E8%88%AA%E5%A4%A9+%E7%94%9F%E6%97%A5%E5%BF%AB%E4%B9%90", "extra": {"rank": 4, "raw_score": "7616598", "api_source": "tianapi", "translation": "Happy Birthday, China Aerospace..."}}, {"title": "5. “医生建议上班前三天少干活”", "value": "指数 7524033", "url": "https://weixin.sogou.com/weixin?type=2&query=%E2%80%9C%E5%8C%BB%E7%94%9F%E5%BB%BA%E8%AE%AE%E4%B8%8A%E7%8F%AD%E5%89%8D%E4%B8%89%E5%A4%A9%E5%B0%91%E5%B9%B2%E6%B4%BB%E2%80%9D", "extra": {"rank": 5, "raw_score": "7524033", "api_source": "tianapi", "translation": "\"Doctor suggests to work less three days before starting.\""}}, {"title": "6. 加沙民众街头欢呼庆祝停火协议达成", "value": "指数 7424983", "url": "https://weixin.sogou.com/weixin?type=2&query=%E5%8A%A0%E6%B2%99%E6%B0%91%E4%BC%97%E8%A1%97%E5%A4%B4%E6%AC%A2%E5%91%BC%E5%BA%86%E7%A5%9D%E5%81%9C%E7%81%AB%E5%8D%8F%E8%AE%AE%E8%BE%BE%E6%88%90", "extra": {"rank": 6, "raw_score": "7424983", "api_source": "tianapi", "translation": "Gaza residents celebrate in the streets over ceasefire..."}}, {"title": "7. 净网：多人发布虚假天气信息被罚", "value": "指数 7333667", "url": "https://weixin.sogou.com/weixin?type=2&query=%E5%87%80%E7%BD%91%EF%BC%9A%E5%A4%9A%E4%BA%BA%E5%8F%91%E5%B8%83%E8%99%9A%E5%81%87%E5%A4%A9%E6%B0%94%E4%BF%A1%E6%81%AF%E8%A2%AB%E7%BD%9A", "extra": {"rank": 7, "raw_score": "7333667", "api_source": "tianapi", "translation": "Clean Internet: Multiple people fined for false weather..."}}, {"title": "8. 重庆女子乘“黄色法拉利”去内蒙古", "value": "指数 7237373", "url": "https://weixin.sogou.com/weixin?type=2&query=%E9%87%8D%E5%BA%86%E5%A5%B3%E5%AD%90%E4%B9%98%E2%80%9C%E9%BB%84%E8%89%B2%E6%B3%95%E6%8B%89%E5%88%A9%E2%80%9D%E5%8E%BB%E5%86%85%E8%92%99%E5%8F%A4", "extra": {"rank": 8, "raw_score": "7237373", "api_source": "tianapi", "translation": "Chongqing woman drives a \"yellow Ferrari\" to Inner..."}}, {"title": "9. 老外成青甘大环线“显眼包”", "value": "指数 7140874", "url": "https://weixin.sogou.com/weixin?type=2&query=%E8%80%81%E5%A4%96%E6%88%90%E9%9D%92%E7%94%98%E5%A4%A7%E7%8E%AF%E7%BA%BF%E2%80%9C%E6%98%BE%E7%9C%BC%E5%8C%85%E2%80%9D", "extra": {"rank": 9, "raw_score": "7140874", "api_source": "tianapi", "translation": "Foreigners become the \"eye-catching package\" on Qinggan..."}}, {"title": "10. 男子假期上高速被收费 真相哭笑不得", "value": "指数 7041150", "url": "https://weixin.sogou.com/weixin?type=2&query=%E7%94%B7%E5%AD%90%E5%81%87%E6%9C%9F%E4%B8%8A%E9%AB%98%E9%80%9F%E8%A2%AB%E6%94%B6%E8%B4%B9+%E7%9C%9F%E7%9B%B8%E5%93%AD%E7%AC%91%E4%B8%8D%E5%BE%97", "extra": {"rank": 10, "raw_score": "7041150", "api_source": "tianapi", "translation": "Man charged on highway during vacation; the truth is..."}}]}