{"as_of": "2025-11-21T18:38:23+08:00", "source": "Tencent WeChat Hot Topics", "items": [{"title": "1. 习近平总书记关切事", "value": "指数 7903922", "url": "https://weixin.sogou.com/weixin?type=2&query=%E4%B9%A0%E8%BF%91%E5%B9%B3%E6%80%BB%E4%B9%A6%E8%AE%B0%E5%85%B3%E5%88%87%E4%BA%8B", "extra": {"rank": 1, "raw_score": "7903922", "api_source": "tianapi", "translation": "General Secretary Xi Jinping's concerns..."}}, {"title": "2. 中国驻日使馆重申敌国条款", "value": "指数 7809375", "url": "https://weixin.sogou.com/weixin?type=2&query=%E4%B8%AD%E5%9B%BD%E9%A9%BB%E6%97%A5%E4%BD%BF%E9%A6%86%E9%87%8D%E7%94%B3%E6%95%8C%E5%9B%BD%E6%9D%A1%E6%AC%BE", "extra": {"rank": 2, "raw_score": "7809375", "api_source": "tianapi", "translation": "Chinese Embassy in Japan reiterates enemy country clause..."}}, {"title": "3. 俄发布日本1945年投降画面警告日本", "value": "指数 7712183", "url": "https://weixin.sogou.com/weixin?type=2&query=%E4%BF%84%E5%8F%91%E5%B8%83%E6%97%A5%E6%9C%AC1945%E5%B9%B4%E6%8A%95%E9%99%8D%E7%94%BB%E9%9D%A2%E8%AD%A6%E5%91%8A%E6%97%A5%E6%9C%AC", "extra": {"rank": 3, "raw_score": "7712183", "api_source": "tianapi", "translation": "Russia releases 1945 Japan surrender footage, warns Japan..."}}, {"title": "4. 这是十五运会老将的最后一舞", "value": "指数 7616854", "url": "https://weixin.sogou.com/weixin?type=2&query=%E8%BF%99%E6%98%AF%E5%8D%81%E4%BA%94%E8%BF%90%E4%BC%9A%E8%80%81%E5%B0%86%E7%9A%84%E6%9C%80%E5%90%8E%E4%B8%80%E8%88%9E", "extra": {"rank": 4, "raw_score": "7616854", "api_source": "tianapi", "translation": "This is the last dance for the veteran at the 15th Games..."}}, {"title": "5. 外交部回应高市早苗最新涉华言论", "value": "指数 7521414", "url": "https://weixin.sogou.com/weixin?type=2&query=%E5%A4%96%E4%BA%A4%E9%83%A8%E5%9B%9E%E5%BA%94%E9%AB%98%E5%B8%82%E6%97%A9%E8%8B%97%E6%9C%80%E6%96%B0%E6%B6%89%E5%8D%8E%E8%A8%80%E8%AE%BA", "extra": {"rank": 5, "raw_score": "7521414", "api_source": "tianapi", "translation": "The Foreign Ministry responds to Takashima's latest..."}}, {"title": "6. 39人粤语合唱团竟只有1人会粤语", "value": "指数 7428002", "url": "https://weixin.sogou.com/weixin?type=2&query=39%E4%BA%BA%E7%B2%A4%E8%AF%AD%E5%90%88%E5%94%B1%E5%9B%A2%E7%AB%9F%E5%8F%AA%E6%9C%891%E4%BA%BA%E4%BC%9A%E7%B2%A4%E8%AF%AD", "extra": {"rank": 6, "raw_score": "7428002", "api_source": "tianapi", "translation": "39-member Cantonese choir has only 1 person who speaks..."}}, {"title": "7. 美海军开始打捞南海坠毁的军机", "value": "指数 7331123", "url": "https://weixin.sogou.com/weixin?type=2&query=%E7%BE%8E%E6%B5%B7%E5%86%9B%E5%BC%80%E5%A7%8B%E6%89%93%E6%8D%9E%E5%8D%97%E6%B5%B7%E5%9D%A0%E6%AF%81%E7%9A%84%E5%86%9B%E6%9C%BA", "extra": {"rank": 7, "raw_score": "7331123", "api_source": "tianapi", "translation": "US Navy begins recovery of crashed military aircraft in..."}}, {"title": "8. 男子请陪产假被开除 公司称纯属算计", "value": "指数 7232693", "url": "https://weixin.sogou.com/weixin?type=2&query=%E7%94%B7%E5%AD%90%E8%AF%B7%E9%99%AA%E4%BA%A7%E5%81%87%E8%A2%AB%E5%BC%80%E9%99%A4+%E5%85%AC%E5%8F%B8%E7%A7%B0%E7%BA%AF%E5%B1%9E%E7%AE%97%E8%AE%A1", "extra": {"rank": 8, "raw_score": "7232693", "api_source": "tianapi", "translation": "Man fired for paternity leave; company claims it's a..."}}, {"title": "9. 广西女子被传在柬埔寨劫囚 当地回应", "value": "指数 7136634", "url": "https://weixin.sogou.com/weixin?type=2&query=%E5%B9%BF%E8%A5%BF%E5%A5%B3%E5%AD%90%E8%A2%AB%E4%BC%A0%E5%9C%A8%E6%9F%AC%E5%9F%94%E5%AF%A8%E5%8A%AB%E5%9B%9A+%E5%BD%93%E5%9C%B0%E5%9B%9E%E5%BA%94", "extra": {"rank": 9, "raw_score": "7136634", "api_source": "tianapi", "translation": "Guangxi woman rumored to be kidnapped in Cambodia, local..."}}, {"title": "10. 亲女儿回应老人全网求认干女儿", "value": "指数 7046385", "url": "https://weixin.sogou.com/weixin?type=2&query=%E4%BA%B2%E5%A5%B3%E5%84%BF%E5%9B%9E%E5%BA%94%E8%80%81%E4%BA%BA%E5%85%A8%E7%BD%91%E6%B1%82%E8%AE%A4%E5%B9%B2%E5%A5%B3%E5%84%BF", "extra": {"rank": 10, "raw_score": "7046385", "api_source": "tianapi", "translation": "Daughter responds to elderly man's online request for a..."}}]}