{"as_of": "2025-11-04T22:09:09+08:00", "source": "Tencent WeChat Hot Topics", "items": [{"title": "1. 以开放汇合作之力", "value": "指数 7904885", "url": "https://weixin.sogou.com/weixin?type=2&query=%E4%BB%A5%E5%BC%80%E6%94%BE%E6%B1%87%E5%90%88%E4%BD%9C%E4%B9%8B%E5%8A%9B", "extra": {"rank": 1, "raw_score": "7904885", "api_source": "tianapi", "translation": "Harnessing the power of open collaboration..."}}, {"title": "2. “史上最长”春节假期来了 连休9天", "value": "指数 7807886", "url": "https://weixin.sogou.com/weixin?type=2&query=%E2%80%9C%E5%8F%B2%E4%B8%8A%E6%9C%80%E9%95%BF%E2%80%9D%E6%98%A5%E8%8A%82%E5%81%87%E6%9C%9F%E6%9D%A5%E4%BA%86+%E8%BF%9E%E4%BC%919%E5%A4%A9", "extra": {"rank": 2, "raw_score": "7807886", "api_source": "tianapi", "translation": "The \"longest\" Spring Festival holiday in history: 9 days..."}}, {"title": "3. 2026中秋和国庆假期分开了", "value": "指数 7713078", "url": "https://weixin.sogou.com/weixin?type=2&query=2026%E4%B8%AD%E7%A7%8B%E5%92%8C%E5%9B%BD%E5%BA%86%E5%81%87%E6%9C%9F%E5%88%86%E5%BC%80%E4%BA%86", "extra": {"rank": 3, "raw_score": "7713078", "api_source": "tianapi", "translation": "The Mid-Autumn Festival and National Day holidays in..."}}, {"title": "4. 今年APEC会议有哪些成果", "value": "指数 7615906", "url": "https://weixin.sogou.com/weixin?type=2&query=%E4%BB%8A%E5%B9%B4APEC%E4%BC%9A%E8%AE%AE%E6%9C%89%E5%93%AA%E4%BA%9B%E6%88%90%E6%9E%9C", "extra": {"rank": 4, "raw_score": "7615906", "api_source": "tianapi", "translation": "What are the outcomes of this year's APEC meeting?"}}, {"title": "5. 合肥站保洁员认真擦座椅意外走红", "value": "指数 7521977", "url": "https://weixin.sogou.com/weixin?type=2&query=%E5%90%88%E8%82%A5%E7%AB%99%E4%BF%9D%E6%B4%81%E5%91%98%E8%AE%A4%E7%9C%9F%E6%93%A6%E5%BA%A7%E6%A4%85%E6%84%8F%E5%A4%96%E8%B5%B0%E7%BA%A2", "extra": {"rank": 5, "raw_score": "7521977", "api_source": "tianapi", "translation": "Hefei station cleaner gains fame for diligently wiping..."}}, {"title": "6. 网友花37.9元网购椅子收到一张图纸", "value": "指数 7429079", "url": "https://weixin.sogou.com/weixin?type=2&query=%E7%BD%91%E5%8F%8B%E8%8A%B137.9%E5%85%83%E7%BD%91%E8%B4%AD%E6%A4%85%E5%AD%90%E6%94%B6%E5%88%B0%E4%B8%80%E5%BC%A0%E5%9B%BE%E7%BA%B8", "extra": {"rank": 6, "raw_score": "7429079", "api_source": "tianapi", "translation": "Netizen spends 37.9 yuan on a chair, receives a blueprint..."}}, {"title": "7. 为防白嫖式退货 卖家选用巨型吊牌", "value": "指数 7329709", "url": "https://weixin.sogou.com/weixin?type=2&query=%E4%B8%BA%E9%98%B2%E7%99%BD%E5%AB%96%E5%BC%8F%E9%80%80%E8%B4%A7+%E5%8D%96%E5%AE%B6%E9%80%89%E7%94%A8%E5%B7%A8%E5%9E%8B%E5%90%8A%E7%89%8C", "extra": {"rank": 7, "raw_score": "7329709", "api_source": "tianapi", "translation": "To prevent free returns, sellers use giant tags..."}}, {"title": "8. 世界最大岛正在缓缓漂走", "value": "指数 7231745", "url": "https://weixin.sogou.com/weixin?type=2&query=%E4%B8%96%E7%95%8C%E6%9C%80%E5%A4%A7%E5%B2%9B%E6%AD%A3%E5%9C%A8%E7%BC%93%E7%BC%93%E6%BC%82%E8%B5%B0", "extra": {"rank": 8, "raw_score": "7231745", "api_source": "tianapi", "translation": "The world's largest island is slowly drifting away..."}}, {"title": "9. 发明固体杨枝甘露的人是天才", "value": "指数 7142570", "url": "https://weixin.sogou.com/weixin?type=2&query=%E5%8F%91%E6%98%8E%E5%9B%BA%E4%BD%93%E6%9D%A8%E6%9E%9D%E7%94%98%E9%9C%B2%E7%9A%84%E4%BA%BA%E6%98%AF%E5%A4%A9%E6%89%8D", "extra": {"rank": 9, "raw_score": "7142570", "api_source": "tianapi", "translation": "The inventor of solid mango sago is a genius..."}}, {"title": "10. 2026年放假安排公布", "value": "指数 7040080", "url": "https://weixin.sogou.com/weixin?type=2&query=2026%E5%B9%B4%E6%94%BE%E5%81%87%E5%AE%89%E6%8E%92%E5%85%AC%E5%B8%83", "extra": {"rank": 10, "raw_score": "7040080", "api_source": "tianapi", "translation": "2026 holiday schedule announced..."}}]}