{"as_of": "2025-10-19T18:35:24+08:00", "source": "Weibo Hot Search", "items": [{"title": "1. 卢浮宫多件藏品被盗", "value": "1178859 热度", "url": "https://m.weibo.cn/search?containerid=100103type%3D1%26q%3D%E5%8D%A2%E6%B5%AE%E5%AE%AB%E5%A4%9A%E4%BB%B6%E8%97%8F%E5%93%81%E8%A2%AB%E7%9B%97&v_p=42", "extra": {"rank": 1, "raw_score": " 1178859", "tag": "\n                                                                \n                                    \n                                \n                                                            ", "api_source": "tianapi", "translation": "Multiple artifacts stolen from the Louvre..."}}, {"title": "2. 当年微信可是求着我上线 [新]", "value": "1116370 热度", "url": "https://m.weibo.cn/search?containerid=100103type%3D1%26q%3D%E5%BD%93%E5%B9%B4%E5%BE%AE%E4%BF%A1%E5%8F%AF%E6%98%AF%E6%B1%82%E7%9D%80%E6%88%91%E4%B8%8A%E7%BA%BF&v_p=42", "extra": {"rank": 2, "raw_score": " 1116370", "tag": "新", "api_source": "tianapi", "translation": "Back then, WeChat was eager for me to join..."}}, {"title": "3. 4K修复志愿军跨过鸭绿江影像", "value": "248675 热度", "url": "https://m.weibo.cn/search?containerid=100103type%3D1%26q%3D4K%E4%BF%AE%E5%A4%8D%E5%BF%97%E6%84%BF%E5%86%9B%E8%B7%A8%E8%BF%87%E9%B8%AD%E7%BB%BF%E6%B1%9F%E5%BD%B1%E5%83%8F&v_p=42", "extra": {"rank": 3, "raw_score": " 248675", "tag": "\n                                                                \n                                    \n                                \n                                                            ", "api_source": "tianapi", "translation": "4K restoration of Volunteer Army crossing the Yalu River..."}}, {"title": "4. 官方双11上淘宝明晚8点开卖", "value": "", "url": "https://m.weibo.cn/search?containerid=100103type%3D1%26q%3D%E5%AE%98%E6%96%B9%E5%8F%8C11%E4%B8%8A%E6%B7%98%E5%AE%9D%E6%98%8E%E6%99%9A8%E7%82%B9%E5%BC%80%E5%8D%96&v_p=42", "extra": {"rank": 4, "raw_score": " ", "tag": "", "api_source": "tianapi", "translation": "Official Double 11 sale on Taobao starts tomorrow at 8 PM..."}}, {"title": "5. 以色列空袭加沙南部拉法地区", "value": "234941 热度", "url": "https://m.weibo.cn/search?containerid=100103type%3D1%26q%3D%E4%BB%A5%E8%89%B2%E5%88%97%E7%A9%BA%E8%A2%AD%E5%8A%A0%E6%B2%99%E5%8D%97%E9%83%A8%E6%8B%89%E6%B3%95%E5%9C%B0%E5%8C%BA&v_p=42", "extra": {"rank": 5, "raw_score": " 234941", "tag": "\n                                                            ", "api_source": "tianapi", "translation": "Israeli airstrikes hit Rafah in southern Gaza..."}}, {"title": "6. 卢浮宫持械抢劫事件 [大卖]", "value": "224849 热度", "url": "https://m.weibo.cn/search?containerid=100103type%3D1%26q%3D%E5%8D%A2%E6%B5%AE%E5%AE%AB%E6%8C%81%E6%A2%B0%E6%8A%A2%E5%8A%AB%E4%BA%8B%E4%BB%B6&v_p=42", "extra": {"rank": 6, "raw_score": " 224849", "tag": "大卖", "api_source": "tianapi", "translation": "Louvre armed robbery incident..."}}, {"title": "7. 杨振宁父亲", "value": "224476 热度", "url": "https://m.weibo.cn/search?containerid=100103type%3D1%26q%3D%E6%9D%A8%E6%8C%AF%E5%AE%81%E7%88%B6%E4%BA%B2&v_p=42", "extra": {"rank": 7, "raw_score": " 224476", "tag": "\n                                                                \n                                    \n                                \n                                                            ", "api_source": "tianapi", "translation": "Yang Zhenning's father."}}, {"title": "8. 新上市药品医保不能报销是谣言", "value": "", "url": "https://m.weibo.cn/search?containerid=100103type%3D1%26q%3D%E6%96%B0%E4%B8%8A%E5%B8%82%E8%8D%AF%E5%93%81%E5%8C%BB%E4%BF%9D%E4%B8%8D%E8%83%BD%E6%8A%A5%E9%94%80%E6%98%AF%E8%B0%A3%E8%A8%80&v_p=42", "extra": {"rank": 8, "raw_score": " ", "tag": "", "api_source": "tianapi", "translation": "Newly launched drugs are not excluded from insurance..."}}, {"title": "9. 农商行员工被要求退回三年过节费", "value": "223890 热度", "url": "https://m.weibo.cn/search?containerid=100103type%3D1%26q%3D%E5%86%9C%E5%95%86%E8%A1%8C%E5%91%98%E5%B7%A5%E8%A2%AB%E8%A6%81%E6%B1%82%E9%80%80%E5%9B%9E%E4%B8%89%E5%B9%B4%E8%BF%87%E8%8A%82%E8%B4%B9&v_p=42", "extra": {"rank": 9, "raw_score": " 223890", "tag": "\n                                                            ", "api_source": "tianapi", "translation": "Rural commercial bank employees asked to return three..."}}, {"title": "10. 翁帆发文纪念杨振宁 [新]", "value": "220697 热度", "url": "https://m.weibo.cn/search?containerid=100103type%3D1%26q%3D%E7%BF%81%E5%B8%86%E5%8F%91%E6%96%87%E7%BA%AA%E5%BF%B5%E6%9D%A8%E6%8C%AF%E5%AE%81&v_p=42", "extra": {"rank": 10, "raw_score": " 220697", "tag": "新", "api_source": "tianapi", "translation": "Weng Fan commemorates Yang Zhenning in a post..."}}]}