{"as_of": "2025-11-12T11:01:05+08:00", "source": "Weibo Hot Search", "items": [{"title": "1. 睡眠超9小时也可能有害", "value": "1087572 热度", "url": "https://m.weibo.cn/search?containerid=100103type%3D1%26q%3D%E7%9D%A1%E7%9C%A0%E8%B6%859%E5%B0%8F%E6%97%B6%E4%B9%9F%E5%8F%AF%E8%83%BD%E6%9C%89%E5%AE%B3&v_p=42", "extra": {"rank": 1, "raw_score": " 1087572", "tag": "\n                                                                \n                                    \n                                \n                                                            ", "api_source": "tianapi", "translation": "Sleeping over 9 hours may also be harmful..."}}, {"title": "2. 邢台一家5口被害案家属发声 [新]", "value": "472271 热度", "url": "https://m.weibo.cn/search?containerid=100103type%3D1%26q%3D%E9%82%A2%E5%8F%B0%E4%B8%80%E5%AE%B65%E5%8F%A3%E8%A2%AB%E5%AE%B3%E6%A1%88%E5%AE%B6%E5%B1%9E%E5%8F%91%E5%A3%B0&v_p=42", "extra": {"rank": 2, "raw_score": " 472271", "tag": "新", "api_source": "tianapi", "translation": "Family of five murder victims in Xingtai speaks out..."}}, {"title": "3. 第十五届全运会", "value": "391140 热度", "url": "https://m.weibo.cn/search?containerid=100103type%3D1%26q%3D%E7%AC%AC%E5%8D%81%E4%BA%94%E5%B1%8A%E5%85%A8%E8%BF%90%E4%BC%9A&v_p=42", "extra": {"rank": 3, "raw_score": " 391140", "tag": "\n                                                                \n                                    \n                                \n                                                            ", "api_source": "tianapi", "translation": "The 15th National Games..."}}, {"title": "4. 央视种草全球好车EZ60 [沸]", "value": "", "url": "https://m.weibo.cn/search?containerid=100103type%3D1%26q%3D%E5%A4%AE%E8%A7%86%E7%A7%8D%E8%8D%89%E5%85%A8%E7%90%83%E5%A5%BD%E8%BD%A6EZ60&v_p=42", "extra": {"rank": 4, "raw_score": " ", "tag": "沸", "api_source": "tianapi", "translation": "CCTV promotes the global good car EZ60..."}}, {"title": "5. 凤凰台上官宣定档", "value": "剧集 376812 热度", "url": "https://m.weibo.cn/search?containerid=100103type%3D1%26q%3D%E5%87%A4%E5%87%B0%E5%8F%B0%E4%B8%8A%E5%AE%98%E5%AE%A3%E5%AE%9A%E6%A1%A3&v_p=42", "extra": {"rank": 5, "raw_score": "剧集 376812", "tag": "\n                                                                \n                                    \n                                \n                                                            ", "api_source": "tianapi", "translation": "Phoenix Platform officially announces the release date..."}}, {"title": "6. Viper BLG [重磅]", "value": "346054 热度", "url": "https://m.weibo.cn/search?containerid=100103type%3D1%26q%3DViper%20BLG&v_p=42", "extra": {"rank": 6, "raw_score": " 346054", "tag": "重磅", "api_source": "tianapi", "translation": "Viper BLG..."}}, {"title": "7. 雷军回应小米双11战绩", "value": "324384 热度", "url": "https://m.weibo.cn/search?containerid=100103type%3D1%26q%3D%E9%9B%B7%E5%86%9B%E5%9B%9E%E5%BA%94%E5%B0%8F%E7%B1%B3%E5%8F%8C11%E6%88%98%E7%BB%A9&v_p=42", "extra": {"rank": 7, "raw_score": " 324384", "tag": "\n                                                                \n                                    \n                                \n                                                            ", "api_source": "tianapi", "translation": "Lei Jun responds to Xiaomi's Double 11 performance..."}}, {"title": "8. 出行得流感怎么办 [新]", "value": "", "url": "https://m.weibo.cn/search?containerid=100103type%3D1%26q%3D%E5%87%BA%E8%A1%8C%E5%BE%97%E6%B5%81%E6%84%9F%E6%80%8E%E4%B9%88%E5%8A%9E&v_p=42", "extra": {"rank": 8, "raw_score": " ", "tag": "新", "api_source": "tianapi", "translation": "What to do if you catch the flu while traveling..."}}, {"title": "9. 盛夏芬德拉女主回应火了", "value": "310054 热度", "url": "https://m.weibo.cn/search?containerid=100103type%3D1%26q%3D%E7%9B%9B%E5%A4%8F%E8%8A%AC%E5%BE%B7%E6%8B%89%E5%A5%B3%E4%B8%BB%E5%9B%9E%E5%BA%94%E7%81%AB%E4%BA%86&v_p=42", "extra": {"rank": 9, "raw_score": " 310054", "tag": "\n                                                                \n                                    \n                                \n                                                            ", "api_source": "tianapi", "translation": "The female lead of \"Summer Fendela\" responds to the hype..."}}, {"title": "10. 朱一龙获最佳男主角提名 [新]", "value": "298605 热度", "url": "https://m.weibo.cn/search?containerid=100103type%3D1%26q%3D%E6%9C%B1%E4%B8%80%E9%BE%99%E8%8E%B7%E6%9C%80%E4%BD%B3%E7%94%B7%E4%B8%BB%E8%A7%92%E6%8F%90%E5%90%8D&v_p=42", "extra": {"rank": 10, "raw_score": " 298605", "tag": "新", "api_source": "tianapi", "translation": "Zhu Yilong nominated for Best Actor..."}}]}