{"as_of": "2025-10-03T18:36:07+08:00", "source": "Weibo Hot Search", "items": [{"title": "1. 庞众望回应女友发布结婚登记照", "value": "1180667 热度", "url": "https://m.weibo.cn/search?containerid=100103type%3D1%26q%3D%E5%BA%9E%E4%BC%97%E6%9C%9B%E5%9B%9E%E5%BA%94%E5%A5%B3%E5%8F%8B%E5%8F%91%E5%B8%83%E7%BB%93%E5%A9%9A%E7%99%BB%E8%AE%B0%E7%85%A7&v_p=42", "extra": {"rank": 1, "raw_score": " 1180667", "tag": "\n                                                                \n                                    \n                                \n                                                            ", "api_source": "tianapi", "translation": "Pang Zhongwang responds to girlfriend's marriage registra..."}}, {"title": "2. 久哲谈清清转辅 [新]", "value": "368265 热度", "url": "https://m.weibo.cn/search?containerid=100103type%3D1%26q%3D%E4%B9%85%E5%93%B2%E8%B0%88%E6%B8%85%E6%B8%85%E8%BD%AC%E8%BE%85&v_p=42", "extra": {"rank": 2, "raw_score": " 368265", "tag": "新", "api_source": "tianapi", "translation": "Jiu Zhe discusses Qingqing's transition to assistant..."}}, {"title": "3. 平凡的劳动者凭什么火出圈", "value": "286316 热度", "url": "https://m.weibo.cn/search?containerid=100103type%3D1%26q%3D%E5%B9%B3%E5%87%A1%E7%9A%84%E5%8A%B3%E5%8A%A8%E8%80%85%E5%87%AD%E4%BB%80%E4%B9%88%E7%81%AB%E5%87%BA%E5%9C%88&v_p=42", "extra": {"rank": 3, "raw_score": " 286316", "tag": "\n                                                                \n                                    \n                                \n                                                            ", "api_source": "tianapi", "translation": "What makes ordinary workers go viral?"}}, {"title": "4. 梨形瘦22斤的杀伤力", "value": "286281 热度", "url": "https://m.weibo.cn/search?containerid=100103type%3D1%26q%3D%E6%A2%A8%E5%BD%A2%E7%98%A622%E6%96%A4%E7%9A%84%E6%9D%80%E4%BC%A4%E5%8A%9B&v_p=42", "extra": {"rank": 4, "raw_score": " 286281", "tag": "", "api_source": "tianapi", "translation": "The impact of losing 22 pounds in a pear shape..."}}, {"title": "5. 景德镇文旅证实鸡排哥计划8日休息", "value": "285518 热度", "url": "https://m.weibo.cn/search?containerid=100103type%3D1%26q%3D%E6%99%AF%E5%BE%B7%E9%95%87%E6%96%87%E6%97%85%E8%AF%81%E5%AE%9E%E9%B8%A1%E6%8E%92%E5%93%A5%E8%AE%A1%E5%88%928%E6%97%A5%E4%BC%91%E6%81%AF&v_p=42", "extra": {"rank": 5, "raw_score": " 285518", "tag": "\n                                                            ", "api_source": "tianapi", "translation": "Jingdezhen cultural tourism confirms Chicken Chop Brother..."}}, {"title": "6. 骨相美 皮相美 [新]", "value": "225859 热度", "url": "https://m.weibo.cn/search?containerid=100103type%3D1%26q%3D%E9%AA%A8%E7%9B%B8%E7%BE%8E%20%E7%9A%AE%E7%9B%B8%E7%BE%8E&v_p=42", "extra": {"rank": 6, "raw_score": " 225859", "tag": "新", "api_source": "tianapi", "translation": "Beauty of bone structure, beauty of appearance..."}}, {"title": "7. 张云龙的破界新朋友", "value": "", "url": "https://m.weibo.cn/search?containerid=100103type%3D1%26q%3D%E5%BC%A0%E4%BA%91%E9%BE%99%E7%9A%84%E7%A0%B4%E7%95%8C%E6%96%B0%E6%9C%8B%E5%8F%8B&v_p=42", "extra": {"rank": 7, "raw_score": " ", "tag": "\n                                                                \n                                    \n                                \n                                                            ", "api_source": "tianapi", "translation": "Zhang Yunlong's new friends breaking boundaries..."}}, {"title": "8. 孙颖莎滑倒 [新]", "value": "223763 热度", "url": "https://m.weibo.cn/search?containerid=100103type%3D1%26q%3D%E5%AD%99%E9%A2%96%E8%8E%8E%E6%BB%91%E5%80%92&v_p=42", "extra": {"rank": 8, "raw_score": " 223763", "tag": "新", "api_source": "tianapi", "translation": "Sun Yingsha slipped..."}}, {"title": "9. TTG战胜TES", "value": "223372 热度", "url": "https://m.weibo.cn/search?containerid=100103type%3D1%26q%3DTTG%E6%88%98%E8%83%9CTES&v_p=42", "extra": {"rank": 9, "raw_score": " 223372", "tag": "\n                                                                \n                                    \n                                \n                                                            ", "api_source": "tianapi", "translation": "TTG defeats TES..."}}, {"title": "10. 全球人民都知道我们放假了", "value": "221265 热度", "url": "https://m.weibo.cn/search?containerid=100103type%3D1%26q%3D%E5%85%A8%E7%90%83%E4%BA%BA%E6%B0%91%E9%83%BD%E7%9F%A5%E9%81%93%E6%88%91%E4%BB%AC%E6%94%BE%E5%81%87%E4%BA%86&v_p=42", "extra": {"rank": 10, "raw_score": " 221265", "tag": "", "api_source": "tianapi", "translation": "The whole world knows we are on holiday..."}}]}