{"as_of": "2025-12-12T18:39:40+08:00", "source": "Weibo Hot Search", "items": [{"title": "1. 北京暴雪", "value": "1116033 热度", "url": "https://m.weibo.cn/search?containerid=100103type%3D1%26q%3D%E5%8C%97%E4%BA%AC%E6%9A%B4%E9%9B%AA&v_p=42", "extra": {"rank": 1, "raw_score": " 1116033", "tag": "\n                                                                \n                                    \n                                \n                                                            ", "api_source": "tianapi", "translation": "Beijing snowstorm..."}}, {"title": "2. 均价500元的手机壳被疯抢", "value": "359042 热度", "url": "https://m.weibo.cn/search?containerid=100103type%3D1%26q%3D%E5%9D%87%E4%BB%B7500%E5%85%83%E7%9A%84%E6%89%8B%E6%9C%BA%E5%A3%B3%E8%A2%AB%E7%96%AF%E6%8A%A2&v_p=42", "extra": {"rank": 2, "raw_score": " 359042", "tag": "", "api_source": "tianapi", "translation": "Phone cases priced at 500 yuan are being snatched up..."}}, {"title": "3. 新形势下经济工作五个必须", "value": "308759 热度", "url": "https://m.weibo.cn/search?containerid=100103type%3D1%26q%3D%E6%96%B0%E5%BD%A2%E5%8A%BF%E4%B8%8B%E7%BB%8F%E6%B5%8E%E5%B7%A5%E4%BD%9C%E4%BA%94%E4%B8%AA%E5%BF%85%E9%A1%BB&v_p=42", "extra": {"rank": 3, "raw_score": " 308759", "tag": "\n                                                            ", "api_source": "tianapi", "translation": "Five essentials for economic work under new circumstances..."}}, {"title": "4. 京东双12国家补贴后再打9折", "value": "", "url": "https://m.weibo.cn/search?containerid=100103type%3D1%26q%3D%E4%BA%AC%E4%B8%9C%E5%8F%8C12%E5%9B%BD%E5%AE%B6%E8%A1%A5%E8%B4%B4%E5%90%8E%E5%86%8D%E6%89%939%E6%8A%98&v_p=42", "extra": {"rank": 4, "raw_score": " ", "tag": "", "api_source": "tianapi", "translation": "JD's Double 12 offers an additional 10% off after..."}}, {"title": "5. 药品说明书1粒米能挡6个字", "value": "305158 热度", "url": "https://m.weibo.cn/search?containerid=100103type%3D1%26q%3D%E8%8D%AF%E5%93%81%E8%AF%B4%E6%98%8E%E4%B9%A61%E7%B2%92%E7%B1%B3%E8%83%BD%E6%8C%A16%E4%B8%AA%E5%AD%97&v_p=42", "extra": {"rank": 5, "raw_score": " 305158", "tag": "\n                                                            ", "api_source": "tianapi", "translation": "One grain of rice can block six characters..."}}, {"title": "6. 白宫回应中日冲突后日本失望 [火热]", "value": "293759 热度", "url": "https://m.weibo.cn/search?containerid=100103type%3D1%26q%3D%E7%99%BD%E5%AE%AB%E5%9B%9E%E5%BA%94%E4%B8%AD%E6%97%A5%E5%86%B2%E7%AA%81%E5%90%8E%E6%97%A5%E6%9C%AC%E5%A4%B1%E6%9C%9B&v_p=42", "extra": {"rank": 6, "raw_score": " 293759", "tag": "火热", "api_source": "tianapi", "translation": "White House responds to Japan's disappointment after..."}}, {"title": "7. 成毅天地剑心降级", "value": "剧集 293604 热度", "url": "https://m.weibo.cn/search?containerid=100103type%3D1%26q%3D%E6%88%90%E6%AF%85%E5%A4%A9%E5%9C%B0%E5%89%91%E5%BF%83%E9%99%8D%E7%BA%A7&v_p=42", "extra": {"rank": 7, "raw_score": "剧集 293604", "tag": "\n                                                                \n                                    \n                                \n                                                            ", "api_source": "tianapi", "translation": "Cheng Yi's \"Heaven and Earth Sword Heart\" downgraded..."}}, {"title": "8. 安全就是吉利 [新]", "value": "", "url": "https://m.weibo.cn/search?containerid=100103type%3D1%26q%3D%E5%AE%89%E5%85%A8%E5%B0%B1%E6%98%AF%E5%90%89%E5%88%A9&v_p=42", "extra": {"rank": 8, "raw_score": " ", "tag": "新", "api_source": "tianapi", "translation": "Safety is prosperity..."}}, {"title": "9. FPX.ZQ战胜成都GG", "value": "292958 热度", "url": "https://m.weibo.cn/search?containerid=100103type%3D1%26q%3DFPX.ZQ%E6%88%98%E8%83%9C%E6%88%90%E9%83%BDGG&v_p=42", "extra": {"rank": 9, "raw_score": " 292958", "tag": "\n                                                                \n                                    \n                                \n                                                            ", "api_source": "tianapi", "translation": "FPX.ZQ defeats Chengdu GG..."}}, {"title": "10. 日本仍有人公然说南京大屠杀是造谣", "value": "292305 热度", "url": "https://m.weibo.cn/search?containerid=100103type%3D1%26q%3D%E6%97%A5%E6%9C%AC%E4%BB%8D%E6%9C%89%E4%BA%BA%E5%85%AC%E7%84%B6%E8%AF%B4%E5%8D%97%E4%BA%AC%E5%A4%A7%E5%B1%A0%E6%9D%80%E6%98%AF%E9%80%A0%E8%B0%A3&v_p=42", "extra": {"rank": 10, "raw_score": " 292305", "tag": "", "api_source": "tianapi", "translation": "Some in Japan still openly claim the Nanjing Massacre is..."}}]}